yolo_labeler/__init__.py
yolo_labeler/yolo_labeler.py
yolo_labeler/utils/data_loader.py
yolo_labeler/utils/u2net.py
yolo_labeler-0.0.3.dist-info/LICENSE
yolo_labeler-0.0.3.dist-info/METADATA
yolo_labeler-0.0.3.dist-info/WHEEL
yolo_labeler-0.0.3.dist-info/top_level.txt
yolo_labeler-0.0.3.dist-info/RECORD
