Metadata-Version: 2.1
Name: yolo-labeler
Version: 0.0.3
Summary: Remove image background and label object in yolo format
Home-page: https://github.com/abpanchal95/yolo-labeler
Author: Abhi Panchal
Author-email: abpanchal95@gmail.com
License: UNKNOWN
Keywords: remove,background,u2net,yolo,labelling,automatic,text,format
Platform: UNKNOWN
Classifier: Programming Language :: Python :: 3
Classifier: License :: OSI Approved :: MIT License
Requires-Python: >=3.6
Requires-Dist: wheel
Requires-Dist: numpy (==1.19.1)
Requires-Dist: pillow (==7.2.0)
Requires-Dist: scikit-image (==0.17.2)
Requires-Dist: torch (==1.6.0)
Requires-Dist: torchvision (==0.7.0)
Requires-Dist: tqdm (==4.48.2)
Requires-Dist: requests (==2.24.0)
Requires-Dist: scipy (==1.5.2)
Requires-Dist: pymatting (==1.0.6)
